[
  {"date": "2025-09-01", "scope1": 1200, "scope2": 800, "scope3": 1500, "total": 3500},
  {"date": "2025-09-02", "scope1": 1250, "scope2": 820, "scope3": 1520, "total": 3590},
  {"date": "2025-09-03", "scope1": 1300, "scope2": 850, "scope3": 1580, "total": 3730},
  {"date": "2025-09-04", "scope1": 1180, "scope2": 790, "scope3": 1450, "total": 3420},
  {"date": "2025-09-05", "scope1": 1225, "scope2": 810, "scope3": 1490, "total": 3525},
  {"date": "2025-09-06", "scope1": 1270, "scope2": 830, "scope3": 1550, "total": 3650},
  {"date": "2025-09-07", "scope1": 1240, "scope2": 805, "scope3": 1515, "total": 3560},
  {"date": "2025-09-08", "scope1": 1290, "scope2": 845, "scope3": 1570, "total": 3705},
  {"date": "2025-09-09", "scope1": 1210, "scope2": 795, "scope3": 1480, "total": 3485},
  {"date": "2025-09-10", "scope1": 1260, "scope2": 825, "scope3": 1540, "total": 3625},
  {"date": "2025-09-11", "scope1": 1230, "scope2": 810, "scope3": 1505, "total": 3545},
  {"date": "2025-09-12", "scope1": 1280, "scope2": 840, "scope3": 1565, "total": 3685},
  {"date": "2025-09-13", "scope1": 1195, "scope2": 785, "scope3": 1470, "total": 3450},
  {"date": "2025-09-14", "scope1": 1245, "scope2": 815, "scope3": 1520, "total": 3580},
  {"date": "2025-09-15", "scope1": 1295, "scope2": 850, "scope3": 1580, "total": 3725},
  {"date": "2025-09-16", "scope1": 1215, "scope2": 800, "scope3": 1490, "total": 3505},
  {"date": "2025-09-17", "scope1": 1265, "scope2": 830, "scope3": 1555, "total": 3650},
  {"date": "2025-09-18", "scope1": 1235, "scope2": 805, "scope3": 1510, "total": 3550},
  {"date": "2025-09-19", "scope1": 1285, "scope2": 845, "scope3": 1575, "total": 3705},
  {"date": "2025-09-20", "scope1": 1205, "scope2": 790, "scope3": 1485, "total": 3480},
  {"date": "2025-09-21", "scope1": 1255, "scope2": 820, "scope3": 1545, "total": 3620},
  {"date": "2025-09-22", "scope1": 1225, "scope2": 810, "scope3": 1505, "total": 3540},
  {"date": "2025-09-23", "scope1": 1275, "scope2": 835, "scope3": 1560, "total": 3670},
  {"date": "2025-09-24", "scope1": 1190, "scope2": 780, "scope3": 1460, "total": 3430},
  {"date": "2025-09-25", "scope1": 1240, "scope2": 815, "scope3": 1520, "total": 3575},
  {"date": "2025-09-26", "scope1": 1290, "scope2": 855, "scope3": 1585, "total": 3730},
  {"date": "2025-09-27", "scope1": 1210, "scope2": 795, "scope3": 1490, "total": 3495},
  {"date": "2025-09-28", "scope1": 1260, "scope2": 825, "scope3": 1550, "total": 3635},
  {"date": "2025-09-29", "scope1": 1230, "scope2": 805, "scope3": 1515, "total": 3550},
  {"date": "2025-09-30", "scope1": 1280, "scope2": 845, "scope3": 1575, "total": 3700}
]
